[
  {
    "slug" : "acanthostega",
    "name" : "acantostega",
    "color1" : "Beige",
    "color2" : "Marrone",
    "source" : "Valutare i fossili"
  },
  {
    "slug" : "amber",
    "name" : "ambra",
    "color1" : "Giallo",
    "color2" : "Giallo",
    "source" : "Valutare i fossili"
  },
  {
    "slug" : "ammonite",
    "name" : "ammonite",
    "color1" : "Beige",
    "color2" : "Marrone",
    "source" : "Valutare i fossili"
  },
  {
    "slug" : "ankylo-skull",
    "name" : "cranio anchilosauro",
    "color1" : "Marrone",
    "color2" : "Marrone",
    "source" : "Valutare i fossili"
  },
  {
    "slug" : "ankylo-tail",
    "name" : "coda anchilosauro",
    "color1" : "Marrone",
    "color2" : "Marrone",
    "source" : "Valutare i fossili"
  },
  {
    "slug" : "ankylo-torso",
    "name" : "torso anchilosauro",
    "color1" : "Marrone",
    "color2" : "Marrone",
    "source" : "Valutare i fossili"
  },
  {
    "slug" : "anomalocaris",
    "name" : "anomalocaride",
    "color1" : "Nero",
    "color2" : "Grigio",
    "source" : "Valutare i fossili"
  },
  {
    "slug" : "archaeopteryx",
    "name" : "archaeopteryx",
    "color1" : "Beige",
    "color2" : "Marrone",
    "source" : "Valutare i fossili"
  },
  {
    "slug" : "archelon-skull",
    "name" : "cranio archelone",
    "color1" : "Marrone",
    "color2" : "Marrone",
    "source" : "Valutare i fossili"
  },
  {
    "slug" : "archelon-tail",
    "name" : "coda archelone",
    "color1" : "Marrone",
    "color2" : "Marrone",
    "source" : "Valutare i fossili"
  },
  {
    "slug" : "australopith",
    "name" : "australopiteco",
    "color1" : "Beige",
    "color2" : "Marrone",
    "source" : "Valutare i fossili"
  },
  {
    "slug" : "brachio-chest",
    "name" : "torace brachiosauro",
    "color1" : "Marrone",
    "color2" : "Marrone",
    "source" : "Valutare i fossili"
  },
  {
    "slug" : "brachio-pelvis",
    "name" : "bacino brachiosauro",
    "color1" : "Marrone",
    "color2" : "Marrone",
    "source" : "Valutare i fossili"
  },
  {
    "slug" : "brachio-skull",
    "name" : "cranio brachiosauro",
    "color1" : "Marrone",
    "color2" : "Marrone",
    "source" : "Valutare i fossili"
  },
  {
    "slug" : "brachio-tail",
    "name" : "coda brachiosauro",
    "color1" : "Marrone",
    "color2" : "Marrone",
    "source" : "Valutare i fossili"
  },
  {
    "slug" : "coprolite",
    "name" : "coprolito",
    "color1" : "Marrone",
    "color2" : "Marrone",
    "source" : "Valutare i fossili"
  },
  {
    "slug" : "deinony-tail",
    "name" : "coda deinonico",
    "color1" : "Marrone",
    "color2" : "Marrone",
    "source" : "Valutare i fossili"
  },
  {
    "slug" : "deinony-torso",
    "name" : "torso deinonico",
    "color1" : "Marrone",
    "color2" : "Marrone",
    "source" : "Valutare i fossili"
  },
  {
    "slug" : "dimetrodon-skull",
    "name" : "cranio dimetrodonte",
    "color1" : "Marrone",
    "color2" : "Marrone",
    "source" : "Valutare i fossili"
  },
  {
    "slug" : "dimetrodon-torso",
    "name" : "torso dimetrodonte",
    "color1" : "Marrone",
    "color2" : "Marrone",
    "source" : "Valutare i fossili"
  },
  {
    "slug" : "dinosaur-track",
    "name" : "orma dinosauro",
    "color1" : "Beige",
    "color2" : "Marrone",
    "source" : "Valutare i fossili"
  },
  {
    "slug" : "diplo-chest",
    "name" : "torso diplodoco",
    "color1" : "Marrone",
    "color2" : "Marrone",
    "source" : "Valutare i fossili"
  },
  {
    "slug" : "diplo-neck",
    "name" : "collo diplodoco",
    "color1" : "Marrone",
    "color2" : "Marrone",
    "source" : "Valutare i fossili"
  },
  {
    "slug" : "diplo-pelvis",
    "name" : "bacino diplodoco",
    "color1" : "Marrone",
    "color2" : "Marrone",
    "source" : "Valutare i fossili"
  },
  {
    "slug" : "diplo-skull",
    "name" : "cranio diplodoco",
    "color1" : "Marrone",
    "color2" : "Marrone",
    "source" : "Valutare i fossili"
  },
  {
    "slug" : "diplo-tail",
    "name" : "coda diplodoco",
    "color1" : "Marrone",
    "color2" : "Marrone",
    "source" : "Valutare i fossili"
  },
  {
    "slug" : "diplo-tail-tip",
    "name" : "punta di coda diplodoco",
    "color1" : "Marrone",
    "color2" : "Marrone",
    "source" : "Valutare i fossili"
  },
  {
    "slug" : "dunkleosteus",
    "name" : "dunkleosteus",
    "color1" : "Grigio",
    "color2" : "Marrone",
    "source" : "Valutare i fossili"
  },
  {
    "slug" : "eusthenopteron",
    "name" : "eustenottero",
    "color1" : "Marrone",
    "color2" : "Marrone",
    "source" : "Valutare i fossili"
  },
  {
    "slug" : "iguanodon-skull",
    "name" : "cranio iguanodonte",
    "color1" : "Marrone",
    "color2" : "Marrone",
    "source" : "Valutare i fossili"
  },
  {
    "slug" : "iguanodon-tail",
    "name" : "coda iguanodonte",
    "color1" : "Marrone",
    "color2" : "Marrone",
    "source" : "Valutare i fossili"
  },
  {
    "slug" : "iguanodon-torso",
    "name" : "torso iguanodonte",
    "color1" : "Marrone",
    "color2" : "Marrone",
    "source" : "Valutare i fossili"
  },
  {
    "slug" : "juramaia",
    "name" : "juramaia",
    "color1" : "Beige",
    "color2" : "Marrone",
    "source" : "Valutare i fossili"
  },
  {
    "slug" : "left-megalo-side",
    "name" : "metà sinistra megalocero",
    "color1" : "Beige",
    "color2" : "Marrone",
    "source" : "Valutare i fossili"
  },
  {
    "slug" : "left-ptera-wing",
    "name" : "ala sinistra pteranodonte",
    "color1" : "Marrone",
    "color2" : "Marrone",
    "source" : "Valutare i fossili"
  },
  {
    "slug" : "left-quetzal-wing",
    "name" : "ala sinistra quetzalcoatlus",
    "color1" : "Marrone",
    "color2" : "Marrone",
    "source" : "Valutare i fossili"
  },
  {
    "slug" : "mammoth-skull",
    "name" : "cranio mammut",
    "color1" : "Beige",
    "color2" : "Marrone",
    "source" : "Valutare i fossili"
  },
  {
    "slug" : "mammoth-torso",
    "name" : "torso mammut",
    "color1" : "Beige",
    "color2" : "Marrone",
    "source" : "Valutare i fossili"
  },
  {
    "slug" : "megacero-skull",
    "name" : "cranio brontoterio",
    "color1" : "Marrone",
    "color2" : "Marrone",
    "source" : "Valutare i fossili"
  },
  {
    "slug" : "megacero-tail",
    "name" : "coda brontoterio",
    "color1" : "Marrone",
    "color2" : "Marrone",
    "source" : "Valutare i fossili"
  },
  {
    "slug" : "megacero-torso",
    "name" : "torso brontoterio",
    "color1" : "Marrone",
    "color2" : "Marrone",
    "source" : "Valutare i fossili"
  },
  {
    "slug" : "myllokunmingia",
    "name" : "myllokunmingia",
    "color1" : "Grigio",
    "color2" : "Grigio",
    "source" : "Valutare i fossili"
  },
  {
    "slug" : "ophthalmo-skull",
    "name" : "cranio oftalmosauro",
    "color1" : "Marrone",
    "color2" : "Marrone",
    "source" : "Valutare i fossili"
  },
  {
    "slug" : "ophthalmo-torso",
    "name" : "torso oftalmosauro",
    "color1" : "Marrone",
    "color2" : "Marrone",
    "source" : "Valutare i fossili"
  },
  {
    "slug" : "pachy-skull",
    "name" : "cranio pachicefalosauro",
    "color1" : "Marrone",
    "color2" : "Marrone",
    "source" : "Valutare i fossili"
  },
  {
    "slug" : "pachy-tail",
    "name" : "coda pachicefalosauro",
    "color1" : "Marrone",
    "color2" : "Marrone",
    "source" : "Valutare i fossili"
  },
  {
    "slug" : "parasaur-skull",
    "name" : "cranio parasauro",
    "color1" : "Marrone",
    "color2" : "Marrone",
    "source" : "Valutare i fossili"
  },
  {
    "slug" : "parasaur-tail",
    "name" : "coda parasauro",
    "color1" : "Marrone",
    "color2" : "Marrone",
    "source" : "Valutare i fossili"
  },
  {
    "slug" : "parasaur-torso",
    "name" : "torso parasauro",
    "color1" : "Marrone",
    "color2" : "Marrone",
    "source" : "Valutare i fossili"
  },
  {
    "slug" : "plesio-body",
    "name" : "corpo plesiosauro",
    "color1" : "Marrone",
    "color2" : "Marrone",
    "source" : "Valutare i fossili"
  },
  {
    "slug" : "plesio-skull",
    "name" : "cranio plesiosauro",
    "color1" : "Marrone",
    "color2" : "Marrone",
    "source" : "Valutare i fossili"
  },
  {
    "slug" : "plesio-tail",
    "name" : "coda plesiosauro",
    "color1" : "Marrone",
    "color2" : "Marrone",
    "source" : "Valutare i fossili"
  },
  {
    "slug" : "ptera-body",
    "name" : "torso pteranodonte",
    "color1" : "Marrone",
    "color2" : "Marrone",
    "source" : "Valutare i fossili"
  },
  {
    "slug" : "quetzal-torso",
    "name" : "torso quetzalcoatlus",
    "color1" : "Marrone",
    "color2" : "Marrone",
    "source" : "Valutare i fossili"
  },
  {
    "slug" : "right-megalo-side",
    "name" : "metà destra megalocero",
    "color1" : "Beige",
    "color2" : "Marrone",
    "source" : "Valutare i fossili"
  },
  {
    "slug" : "right-ptera-wing",
    "name" : "ala destra pteranodonte",
    "color1" : "Marrone",
    "color2" : "Marrone",
    "source" : "Valutare i fossili"
  },
  {
    "slug" : "right-quetzal-wing",
    "name" : "ala destra quetzalcoatlus",
    "color1" : "Marrone",
    "color2" : "Marrone",
    "source" : "Valutare i fossili"
  },
  {
    "slug" : "sabertooth-skull",
    "name" : "cranio smilodonte",
    "color1" : "Marrone",
    "color2" : "Marrone",
    "source" : "Valutare i fossili"
  },
  {
    "slug" : "sabertooth-tail",
    "name" : "coda smilodonte",
    "color1" : "Marrone",
    "color2" : "Marrone",
    "source" : "Valutare i fossili"
  },
  {
    "slug" : "shark-tooth-pattern",
    "name" : "mandibola di elicoprione",
    "color1" : "Beige",
    "color2" : "Marrone",
    "source" : "Valutare i fossili"
  },
  {
    "slug" : "spino-skull",
    "name" : "cranio spinosauro",
    "color1" : "Marrone",
    "color2" : "Marrone",
    "source" : "Valutare i fossili"
  },
  {
    "slug" : "spino-tail",
    "name" : "coda spinosauro",
    "color1" : "Marrone",
    "color2" : "Marrone",
    "source" : "Valutare i fossili"
  },
  {
    "slug" : "spino-torso",
    "name" : "torso spinosauro",
    "color1" : "Marrone",
    "color2" : "Marrone",
    "source" : "Valutare i fossili"
  },
  {
    "slug" : "stego-skull",
    "name" : "cranio stegosauro",
    "color1" : "Marrone",
    "color2" : "Marrone",
    "source" : "Valutare i fossili"
  },
  {
    "slug" : "stego-tail",
    "name" : "coda stegosauro",
    "color1" : "Marrone",
    "color2" : "Marrone",
    "source" : "Valutare i fossili"
  },
  {
    "slug" : "stego-torso",
    "name" : "torso stegosauro",
    "color1" : "Marrone",
    "color2" : "Marrone",
    "source" : "Valutare i fossili"
  },
  {
    "slug" : "t-rex-skull",
    "name" : "cranio tirannosauro",
    "color1" : "Marrone",
    "color2" : "Marrone",
    "source" : "Valutare i fossili"
  },
  {
    "slug" : "t-rex-tail",
    "name" : "coda tirannosauro",
    "color1" : "Marrone",
    "color2" : "Marrone",
    "source" : "Valutare i fossili"
  },
  {
    "slug" : "t-rex-torso",
    "name" : "torso tirannosauro",
    "color1" : "Marrone",
    "color2" : "Marrone",
    "source" : "Valutare i fossili"
  },
  {
    "slug" : "tricera-skull",
    "name" : "cranio triceratopo",
    "color1" : "Marrone",
    "color2" : "Marrone",
    "source" : "Valutare i fossili"
  },
  {
    "slug" : "tricera-tail",
    "name" : "coda triceratopo",
    "color1" : "Marrone",
    "color2" : "Marrone",
    "source" : "Valutare i fossili"
  },
  {
    "slug" : "tricera-torso",
    "name" : "torso triceratopo",
    "color1" : "Marrone",
    "color2" : "Marrone",
    "source" : "Valutare i fossili"
  },
  {
    "slug" : "trilobite",
    "name" : "trilobite",
    "color1" : "Beige",
    "color2" : "Marrone",
    "source" : "Valutare i fossili"
  }
]
